shark561/__init__.py
shark561/moduleA.py
shark561-0.0.3.dist-info/LICENSE
shark561-0.0.3.dist-info/METADATA
shark561-0.0.3.dist-info/WHEEL
shark561-0.0.3.dist-info/top_level.txt
shark561-0.0.3.dist-info/RECORD
