Metadata-Version: 2.1
Name: shark561
Version: 0.0.3
Summary: Test pypi shark
Home-page: https://github.com/Rexmen/shark561.git
Author: Bing
Author-email: binchen561@gmail.com
License: UNKNOWN
Platform: UNKNOWN
Classifier: Programming Language :: Python :: 3
Classifier: License :: OSI Approved :: MIT License
Classifier: Operating System :: OS Independent
Requires-Python: >=3.6.0
License-File: LICENSE
